codegen/__init__.py
codegen/main.py
codegen/controllercodegen/__init__.py
codegen/controllercodegen/codegenerator.py
codegen/controllercodegen/main.py
codegen/controllercodegen/template/__init__.py
codegen/controllercodegen/template/codeblocktemplate.py
codegen/controllercodegen/template/filetemplate.py
codegen/modelcodegen/__init__.py
codegen/modelcodegen/codegen.py
codegen/modelcodegen/main.py
codegen/modelcodegen/dialects/__init__.py
codegen/modelcodegen/dialects/postgresql.py
codegen/modelcodegen/template/__init__.py
codegen/modelcodegen/template/filetemplate.py
codegen/utils/__init__.py
codegen/utils/checkTable.py
codegen/utils/commons.py
codegen/utils/response_code.py
codegen/utils/tablesMetadata.py
sqlalchemy_codegen-1.1.2.dist-info/LICENSE
sqlalchemy_codegen-1.1.2.dist-info/METADATA
sqlalchemy_codegen-1.1.2.dist-info/WHEEL
sqlalchemy_codegen-1.1.2.dist-info/entry_points.txt
sqlalchemy_codegen-1.1.2.dist-info/top_level.txt
sqlalchemy_codegen-1.1.2.dist-info/RECORD
