Metadata-Version: 2.1
Name: sqlalchemy-codegen
Version: 1.1.2
Summary: Automatic generate model layer and controller layer code for SQLAlchemy with Flask support
Author: iDeal-ncepu
License: MIT
Keywords: sqlalchemy,flask-sqlalchemy,sqlacodegen,flask
Classifier: Development Status :: 5 - Production/Stable
Classifier: Intended Audience :: Developers
Classifier: License :: OSI Approved :: MIT License
Classifier: Environment :: Console
Classifier: Topic :: Database
Classifier: Topic :: Software Development :: Code Generators
Classifier: Programming Language :: Python
Classifier: Programming Language :: Python :: 3
Classifier: Programming Language :: Python :: 3.2
Classifier: Programming Language :: Python :: 3.3
Classifier: Programming Language :: Python :: 3.4
Classifier: Programming Language :: Python :: 3.5
Classifier: Programming Language :: Python :: 3.6
Classifier: Programming Language :: Python :: 3.7
Classifier: Programming Language :: Python :: 3.8
Classifier: Programming Language :: Python :: 3.9
Classifier: Programming Language :: Python :: 3.10
Classifier: Programming Language :: Python :: 3.11
Classifier: Programming Language :: Python :: 3.12
License-File: LICENSE
Requires-Dist: SQLAlchemy >=2.0.0
Requires-Dist: inflect >=7.0.0
Requires-Dist: pymysql >=1.0.2
Requires-Dist: loguru >=0.6.0
Requires-Dist: sqlacodegen >=2.3.0
Requires-Dist: greenlet >=3.0.0
